comfyui_character_generator/__about__.py
comfyui_character_generator/__init__.py
comfyui_character_generator/generate.py
comfyui_character_generator/main.py
comfyui_character_generator/bin/generate.sh
comfyui_character_generator/bin/install_nodes.sh
comfyui_character_generator/util/__init__.py
comfyui_character_generator/util/args.py
comfyui_character_generator/util/config.py
comfyui_character_generator/util/constants.py
comfyui_character_generator/util/enums.py
comfyui_character_generator/util/manager.py
comfyui_character_generator/util/operations.py
comfyui_character_generator-0.2.4.dist-info/METADATA
comfyui_character_generator-0.2.4.dist-info/WHEEL
comfyui_character_generator-0.2.4.dist-info/entry_points.txt
comfyui_character_generator-0.2.4.dist-info/RECORD
