Metadata-Version: 2.4
Name: comfyui-character-generator
Version: 0.2.4
Summary: Automated ComfyUI character generator
Project-URL: Homepage, https://github.com/jpchauvel/comfyui-character-generator
Project-URL: Documentation, https://github.com/jpchauvel/comfyui-character-generator/blob/main/README.md
Project-URL: Repository, https://github.com/jpchauvel/comfyui-character-generator
Project-URL: Issues, https://github.com/jpchauvel/comfyui-character-generator/issues
Author-email: Jean-Pierre Chauvel <jean.p.chauvel@gmail.com>
Classifier: Development Status :: 4 - Beta
Classifier: Intended Audience :: Developers
Classifier: Programming Language :: Python :: 3
Classifier: Programming Language :: Python :: 3.12
Classifier: Topic :: Software Development :: Build Tools
Requires-Python: <3.13,>=3.12
